LICENSE
MANIFEST.in
README.rst
requirements.txt
setup.cfg
setup.py
pathsjson/__init__.py
pathsjson/automagic.py
pathsjson/cli.py
pathsjson/helpers.py
pathsjson/impl.py
pathsjson/path.py
pathsjson/resolution.py
pathsjson/schema.json
pathsjson.egg-info/PKG-INFO
pathsjson.egg-info/SOURCES.txt
pathsjson.egg-info/dependency_links.txt
pathsjson.egg-info/entry_points.txt
pathsjson.egg-info/requires.txt
pathsjson.egg-info/top_level.txt
tests/__init__.py
tests/test_path.py
tests/test_pathsjson.py
tests/test_resolution.py